spinda/__init__.py
spinda/cli.py
spinda/spinda.py
spinda-0.1.1.dist-info/AUTHORS.rst
spinda-0.1.1.dist-info/LICENSE
spinda-0.1.1.dist-info/METADATA
spinda-0.1.1.dist-info/WHEEL
spinda-0.1.1.dist-info/entry_points.txt
spinda-0.1.1.dist-info/top_level.txt
spinda-0.1.1.dist-info/RECORD
