Metadata-Version: 2.1
Name: spinda
Version: 0.1.1
Summary: A tool for counting the number of lines of code and object relationships in a project...
Home-page: https://github.com/kaixinbaba/spinda
Author: Jeff Xun
Author-email: 452914639@qq.com
License: GNU General Public License v3
Keywords: spinda
Platform: UNKNOWN
Classifier: Development Status :: 2 - Pre-Alpha
Classifier: Intended Audience :: Developers
Classifier: License :: OSI Approved :: GNU General Public License v3 (GPLv3)
Classifier: Natural Language :: English
Classifier: Programming Language :: Python :: 3
Classifier: Programming Language :: Python :: 3.6
Requires-Dist: Click (>=6.0)
